{"id":"p:242601","name":"Greg Methvin","type":"Person","permalink":"/person/greg-methvin","homepage_url":null,"twitter_username":"gmethvin","logo_url":"0034/1095/341095v2-max-250x250.jpg","logo_width":530,"logo_height":640,"overview":"Greg Methvin is a Founder at Daltic, where he leads their engineering team.\nPreviously, Greg worked at Addepar on their server-side architecture, Web infrastructure, and internal APIs. He also was an early software engineer at FortyTwo.","investment_rounds":null,"invested_companies":null}
