{"id":"c:5000","name":"Netscape","type":"Company","permalink":"/company/netscape","category_code":"software","status":"acquired","founded_at":"1994-04-04","closed_at":null,"domain":"netscape.aol.com","homepage_url":"http://netscape.aol.com","twitter_username":null,"logo_url":"27667v1-max-250x250.png","logo_width":200,"logo_height":54,"short_description":null,"overview":"Netscape Communications Corporation offers development, marketing, sale, and support of enterprise software solutions. Its products include e-commerce infrastructure and e-commerce applications targeted primarily at corporate intranets and extranets, and Internet. The company was formerly known as Mosaic Communications Corporation and changed the name to Netscape Communications Corporation in November, 1994. Netscape Communications Corporation was founded in 1994 and is based in Mountain View, California. Netscape Communications Corporation operates as a subsidiary of AOL Inc.","country_code":"USA","state_code":"CA","city":"Mountain View","investment_rounds":null,"invested_companies":null,"funding_rounds":1,"funding_total_usd":null}
