{"id":"c:58846","name":"Pinterest","type":"Company","permalink":"/company/pinterest","category_code":"social","status":"operating","founded_at":"2009-01-01","closed_at":null,"domain":"pinterest.com","homepage_url":"http://pinterest.com","twitter_username":"Pinterest","logo_url":"174502v6-max-250x250.png","logo_width":250,"logo_height":250,"short_description":"Pinterest is a social networking site with a","overview":"Pinterest is a social networking site with a visually-pleasing \"virtual pinboard\" interface. Users collect photos and link to products they love, creating their own pinboards and following the pinboards of other people whom they find interesting.\nThe site has experienced [rapid growth](http://techcrunch.com/2011/12/22/pinterest-40-fold/) in recent months.","country_code":"USA","state_code":"CA","city":"San Francisco","investment_rounds":null,"invested_companies":null,"funding_rounds":6,"funding_total_usd":562500000}
