{"id":"p:12764","name":"Kevin Cheng","type":"Person","permalink":"/person/kevin-cheng","homepage_url":"http://kevnull.com","twitter_username":"k","logo_url":"0007/0776/70776v3-max-250x250.jpg","logo_width":150,"logo_height":150,"overview":"Kevin Cheng is a Product Manager working on the web client at [Twitter](http://www.crunchbase.com/company/twitter), where he joined in December 2009.\nPreviously, he was the Director of Product Strategy at [Raptr](http://raptr.com), a videogame social network, the co-founder and artist for [OK/ Cancel](http://ok-cancel.com), a webcomic on user experience, and the co-founder of [Off Panel Productions](http://offpanel.com), an online comic publishing network.\nKevin is the author of [See What I Mean](http://seewhatimean.org). He was previously at Yahoo!’s Brickhouse incubator where he designed [Pipes](http://pipes.yahoo.com) and [Bravonation](http://bravonation.com), and at Yahoo! Maps, Yahoo! Local, Adaptive Path, and Trilogy.\nHe holds a Masters degree from University College London in Human Computer Interaction and has presented on strategy and design topics at numerous conferences including the Information Architecture Summit, the User Interface Conference, and South by Southwest.\nKevin blogs at [kev/null](http://kevnull.com) and has been known to [Twitter](http://twitter.com/k).","investment_rounds":null,"invested_companies":null}
