{"id":"p:27275","name":"Jeff Seibert","type":"Person","permalink":"/person/jeff-seibert","homepage_url":null,"twitter_username":"jeffseibert","logo_url":"0006/1856/61856v2-max-250x250.jpg","logo_width":250,"logo_height":250,"overview":"Jeff Seibert is an experienced serial-entrepreneur with a passion for deeply technical Internet software. His latest company, Crashlytics, was acquired by Twitter in January of 2013, where he is now a Director of Engineering.\nPreviously, Seibert was the CEO of Crashlytics, which he co-founded in 2011 with Wayne Chang. Crashlytics delivered crash analysis tools for iOS and Android apps via an SDK that reached 300 Million mobile devices worldwide.\nIn 2007, Seibert co-founded Increo and served as its COO and lead architect until its acquisition by Box in August of 2009. He subsequently oversaw the integration of Increo","investment_rounds":null,"invested_companies":null}
